bpan/__init__.py
bpan/_version.py
bpan/main.py
bpan/src.py
bpan/utils.py
bpan-1.0.0.dist-info/LICENSE
bpan-1.0.0.dist-info/METADATA
bpan-1.0.0.dist-info/WHEEL
bpan-1.0.0.dist-info/entry_points.txt
bpan-1.0.0.dist-info/top_level.txt
bpan-1.0.0.dist-info/RECORD
