Metadata-Version: 2.1
Name: bpan
Version: 1.0.0
Home-page: https://github.com/yodeng/bpan
License: MIT
Requires-Python: >=3.7
License-File: LICENSE
Requires-Dist: Cython
Requires-Dist: requests
Requires-Dist: requests-toolbelt
Requires-Dist: tqdm
Requires-Dist: urllib3
Requires-Dist: prettytable
